{
  "version": 2,
  "extractor": "pdffigures2",
  "figures": [
    {
      "url": "assets/figures/arxiv/2605.27964v1/fig-001.webp",
      "caption": "Fig. 4. Risk field snapshots for four ablation settings on the same highway merge scene: source-only, +diffusion, +advection, and full DRIFT (+geometrycoupled decay).",
      "page": 6,
      "index": 1,
      "width": 1056,
      "height": 277
    },
    {
      "url": "assets/figures/arxiv/2605.27964v1/fig-002.webp",
      "caption": "Fig. 1. Overall structure of the PDE-based risk inference via field transmission framework for human-like autonomous driving.",
      "page": 2,
      "index": 2,
      "width": 879,
      "height": 460
    },
    {
      "url": "assets/figures/arxiv/2605.27964v1/fig-003.webp",
      "caption": "TABLE I SELECTED PDE AND SOURCE PARAMETERS.",
      "page": 4,
      "index": 3,
      "width": 519,
      "height": 412
    },
    {
      "url": "assets/figures/arxiv/2605.27964v1/fig-004.webp",
      "caption": "TABLE II PERFORMANCE COMPARISON ACROSS ALL METRICS. “–” DENOTES METRICS THAT ARE STRUCTURALLY UNDEFINED FOR NON-TEMPORAL (STATIC) FORMULATIONS.",
      "page": 5,
      "index": 4,
      "width": 1040,
      "height": 282
    },
    {
      "url": "assets/figures/arxiv/2605.27964v1/fig-005.webp",
      "caption": "Fig. 3. Risk field modeling on historical ego trajectories recorded in various traffic scenarios.",
      "page": 5,
      "index": 5,
      "width": 846,
      "height": 481
    }
  ]
}